{"ret": 200, "msg": "声音播放数据", "data": {"uid": 0, "albumId": 9723091, "sort": 0, "pageNum": 5, "pageSize": 30, "tracksAudioPlay": [{"index": 121, "trackId": 46222440, "trackName": "《嫂夫人》郭德纲 于谦", "trackUrl": "/xiangsheng/9723091/46222440", "trackCoverPath": "//imagev2.xmcdn.com/group31/M07/0E/5B/wKgJX1mAQg2SWaYDAAAw0CICWi8444.jpg!op_type=5&upload_type=cover&device_type=ios&name=web_meduim&strip=1&quality=7", "albumId": 9723091, "sourceAlbumId": 9723091, "albumName": "郭德纲21年相声精选", "albumUrl": "/xiangsheng/9723091/", "anchorId": 1000202, "canPlay": true, "isBaiduMusic": false, "isPaid": false, "duration": 2074, "src": "http://audio.xmcdn.com/group30/M0A/8E/1F/wKgJXlmEN2OAdNZdAP_-fXxCI5I766.m4a", "hasBuy": true, "albumIsSample": false, "sampleDuration": 0, "updateTime": "1年前", "createTime": "1年前", "isLike": false, "isCopyright": true}, {"index": 122, "trackId": 46222390, "trackName": "《京中名妓》郭德纲 于谦", "trackUrl": "/xiangsheng/9723091/46222390", "trackCoverPath": "//imagev2.xmcdn.com/group31/M07/0E/5B/wKgJX1mAQg2SWaYDAAAw0CICWi8444.jpg!op_type=5&upload_type=cover&device_type=ios&name=web_meduim&strip=1&quality=7", "albumId": 9723091, "sourceAlbumId": 9723091, "albumName": "郭德纲21年相声精选", "albumUrl": "/xiangsheng/9723091/", "anchorId": 1000202, "canPlay": true, "isBaiduMusic": false, "isPaid": false, "duration": 1660, "src": "http://audio.xmcdn.com/group31/M00/49/4D/wKgJX1mEN1qxB0BGAMzme0eKkVM129.m4a", "hasBuy": true, "albumIsSample": false, "sampleDuration": 0, "updateTime": "1年前", "createTime": "1年前", "isLike": false, "isCopyright": true}, {"index": 123, "trackId": 46222392, "trackName": "《西瓜地的故事》郭德纲 于谦 高峰", "trackUrl": "/xiangsheng/9723091/46222392", "trackCoverPath": "//imagev2.xmcdn.com/group31/M07/0E/5B/wKgJX1mAQg2SWaYDAAAw0CICWi8444.jpg!op_type=5&upload_type=cover&device_type=ios&name=web_meduim&strip=1&quality=7", "albumId": 9723091, "sourceAlbumId": 9723091, "albumName": "郭德纲21年相声精选", "albumUrl": "/xiangsheng/9723091/", "anchorId": 1000202, "canPlay": true, "isBaiduMusic": false, "isPaid": false, "duration": 1656, "src": "http://audio.xmcdn.com/group31/M00/49/4D/wKgJX1mEN13iksXYAMxoYbnuec0035.m4a", "hasBuy": true, "albumIsSample": false, "sampleDuration": 0, "updateTime": "1年前", "createTime": "1年前", "isLike": false, "isCopyright": true}, {"index": 124, "trackId": 46222446, "trackName": "《五星级酒店》郭德纲 于谦", "trackUrl": "/xiangsheng/9723091/46222446", "trackCoverPath": "//imagev2.xmcdn.com/group31/M07/0E/5B/wKgJX1mAQg2SWaYDAAAw0CICWi8444.jpg!op_type=5&upload_type=cover&device_type=ios&name=web_meduim&strip=1&quality=7", "albumId": 9723091, "sourceAlbumId": 9723091, "albumName": "郭德纲21年相声精选", "albumUrl": "/xiangsheng/9723091/", "anchorId": 1000202, "canPlay": true, "isBaiduMusic": false, "isPaid": false, "duration": 1912, "src": "http://audio.xmcdn.com/group30/M0A/8E/21/wKgJXlmEN2rR7LtrAOwDZTe3KmI104.m4a", "hasBuy": true, "albumIsSample": false, "sampleDuration": 0, "updateTime": "1年前", "createTime": "1年前", "isLike": false, "isCopyright": true}, {"index": 125, "trackId": 46222451, "trackName": "《宇宙牌香烟》郭德纲 于谦", "trackUrl": "/xiangsheng/9723091/46222451", "trackCoverPath": "//imagev2.xmcdn.com/group31/M07/0E/5B/wKgJX1mAQg2SWaYDAAAw0CICWi8444.jpg!op_type=5&upload_type=cover&device_type=ios&name=web_meduim&strip=1&quality=7", "albumId": 9723091, "sourceAlbumId": 9723091, "albumName": "郭德纲21年相声精选", "albumUrl": "/xiangsheng/9723091/", "anchorId": 1000202, "canPlay": true, "isBaiduMusic": false, "isPaid": false, "duration": 1701, "src": "http://audio.xmcdn.com/group30/M0A/8E/21/wKgJXlmEN2TRE6MdANHy2jOcmtI481.m4a", "hasBuy": true, "albumIsSample": false, "sampleDuration": 0, "updateTime": "1年前", "createTime": "1年前", "isLike": false, "isCopyright": true}, {"index": 126, "trackId": 46222454, "trackName": "《肛裂的汉子》郭德纲 于谦", "trackUrl": "/xiangsheng/9723091/46222454", "trackCoverPath": "//imagev2.xmcdn.com/group31/M07/0E/5B/wKgJX1mAQg2SWaYDAAAw0CICWi8444.jpg!op_type=5&upload_type=cover&device_type=ios&name=web_meduim&strip=1&quality=7", "albumId": 9723091, "sourceAlbumId": 9723091, "albumName": "郭德纲21年相声精选", "albumUrl": "/xiangsheng/9723091/", "anchorId": 1000202, "canPlay": true, "isBaiduMusic": false, "isPaid": false, "duration": 1931, "src": "http://audio.xmcdn.com/group30/M0A/8E/23/wKgJXlmEN22zkEfOAO5UGyXiBUg223.m4a", "hasBuy": true, "albumIsSample": false, "sampleDuration": 0, "updateTime": "1年前", "createTime": "1年前", "isLike": false, "isCopyright": true}, {"index": 127, "trackId": 46222604, "trackName": "《情义谱》02郭德纲 于谦", "trackUrl": "/xiangsheng/9723091/46222604", "trackCoverPath": "//imagev2.xmcdn.com/group31/M07/0E/5B/wKgJX1mAQg2SWaYDAAAw0CICWi8444.jpg!op_type=5&upload_type=cover&device_type=ios&name=web_meduim&strip=1&quality=7", "albumId": 9723091, "sourceAlbumId": 9723091, "albumName": "郭德纲21年相声精选", "albumUrl": "/xiangsheng/9723091/", "anchorId": 1000202, "canPlay": true, "isBaiduMusic": false, "isPaid": false, "duration": 2732, "src": "http://audio.xmcdn.com/group31/M02/49/50/wKgJX1mEN6HixAdLAVE9cAK9kvg142.m4a", "hasBuy": true, "albumIsSample": false, "sampleDuration": 0, "updateTime": "1年前", "createTime": "1年前", "isLike": false, "isCopyright": true}, {"index": 128, "trackId": 46222610, "trackName": "《情义谱》01郭德纲 于谦", "trackUrl": "/xiangsheng/9723091/46222610", "trackCoverPath": "//imagev2.xmcdn.com/group31/M07/0E/5B/wKgJX1mAQg2SWaYDAAAw0CICWi8444.jpg!op_type=5&upload_type=cover&device_type=ios&name=web_meduim&strip=1&quality=7", "albumId": 9723091, "sourceAlbumId": 9723091, "albumName": "郭德纲21年相声精选", "albumUrl": "/xiangsheng/9723091/", "anchorId": 1000202, "canPlay": true, "isBaiduMusic": false, "isPaid": false, "duration": 2701, "src": "http://audio.xmcdn.com/group31/M02/49/4E/wKgJSVmEN6ih_GCFAU1Md9pD9XA003.m4a", "hasBuy": true, "albumIsSample": false, "sampleDuration": 0, "updateTime": "1年前", "createTime": "1年前", "isLike": false, "isCopyright": true}, {"index": 129, "trackId": 46222455, "trackName": "《民以食为天》郭德纲 于谦", "trackUrl": "/xiangsheng/9723091/46222455", "trackCoverPath": "//imagev2.xmcdn.com/group31/M07/0E/5B/wKgJX1mAQg2SWaYDAAAw0CICWi8444.jpg!op_type=5&upload_type=cover&device_type=ios&name=web_meduim&strip=1&quality=7", "albumId": 9723091, "sourceAlbumId": 9723091, "albumName": "郭德纲21年相声精选", "albumUrl": "/xiangsheng/9723091/", "anchorId": 1000202, "canPlay": true, "isBaiduMusic": false, "isPaid": false, "duration": 860, "src": "http://audio.xmcdn.com/group30/M0A/8E/2C/wKgJXlmEN4GhNf6vAGonmBvnqZc892.m4a", "hasBuy": true, "albumIsSample": false, "sampleDuration": 0, "updateTime": "1年前", "createTime": "1年前", "isLike": false, "isCopyright": true}, {"index": 130, "trackId": 46222608, "trackName": "《坏学生》郭德纲 于谦", "trackUrl": "/xiangsheng/9723091/46222608", "trackCoverPath": "//imagev2.xmcdn.com/group31/M07/0E/5B/wKgJX1mAQg2SWaYDAAAw0CICWi8444.jpg!op_type=5&upload_type=cover&device_type=ios&name=web_meduim&strip=1&quality=7", "albumId": 9723091, "sourceAlbumId": 9723091, "albumName": "郭德纲21年相声精选", "albumUrl": "/xiangsheng/9723091/", "anchorId": 1000202, "canPlay": true, "isBaiduMusic": false, "isPaid": false, "duration": 2191, "src": "http://audio.xmcdn.com/group31/M02/49/51/wKgJX1mEN5-QjmroAQ5tyoyLipw619.m4a", "hasBuy": true, "albumIsSample": false, "sampleDuration": 0, "updateTime": "1年前", "createTime": "1年前", "isLike": false, "isCopyright": true}, {"index": 131, "trackId": 46222612, "trackName": "《沉痛的介绍》郭德纲 于谦", "trackUrl": "/xiangsheng/9723091/46222612", "trackCoverPath": "//imagev2.xmcdn.com/group31/M07/0E/5B/wKgJX1mAQg2SWaYDAAAw0CICWi8444.jpg!op_type=5&upload_type=cover&device_type=ios&name=web_meduim&strip=1&quality=7", "albumId": 9723091, "sourceAlbumId": 9723091, "albumName": "郭德纲21年相声精选", "albumUrl": "/xiangsheng/9723091/", "anchorId": 1000202, "canPlay": true, "isBaiduMusic": false, "isPaid": false, "duration": 2091, "src": "http://audio.xmcdn.com/group31/M02/49/52/wKgJX1mEN6TjCBXSAQIdCxQguz0364.m4a", "hasBuy": true, "albumIsSample": false, "sampleDuration": 0, "updateTime": "1年前", "createTime": "1年前", "isLike": false, "isCopyright": true}, {"index": 132, "trackId": 46222613, "trackName": "《好玩不如嫂子》郭德纲 于谦 ", "trackUrl": "/xiangsheng/9723091/46222613", "trackCoverPath": "//imagev2.xmcdn.com/group31/M07/0E/5B/wKgJX1mAQg2SWaYDAAAw0CICWi8444.jpg!op_type=5&upload_type=cover&device_type=ios&name=web_meduim&strip=1&quality=7", "albumId": 9723091, "sourceAlbumId": 9723091, "albumName": "郭德纲21年相声精选", "albumUrl": "/xiangsheng/9723091/", "anchorId": 1000202, "canPlay": true, "isBaiduMusic": false, "isPaid": false, "duration": 1826, "src": "http://audio.xmcdn.com/group31/M02/49/51/wKgJX1mEN6CQWJtNAOFWg0aAz18263.m4a", "hasBuy": true, "albumIsSample": false, "sampleDuration": 0, "updateTime": "1年前", "createTime": "1年前", "isLike": false, "isCopyright": true}, {"index": 133, "trackId": 46222724, "trackName": "《特级烧烤师》", "trackUrl": "/xiangsheng/9723091/46222724", "trackCoverPath": "//imagev2.xmcdn.com/group31/M07/0E/5B/wKgJX1mAQg2SWaYDAAAw0CICWi8444.jpg!op_type=5&upload_type=cover&device_type=ios&name=web_meduim&strip=1&quality=7", "albumId": 9723091, "sourceAlbumId": 9723091, "albumName": "郭德纲21年相声精选", "albumUrl": "/xiangsheng/9723091/", "anchorId": 1000202, "canPlay": true, "isBaiduMusic": false, "isPaid": false, "duration": 927, "src": "http://audio.xmcdn.com/group31/M02/49/57/wKgJX1mEN7qhou70AHJpO118BEc885.m4a", "hasBuy": true, "albumIsSample": false, "sampleDuration": 0, "updateTime": "1年前", "createTime": "1年前", "isLike": false, "isCopyright": true}, {"index": 134, "trackId": 46222785, "trackName": "《讨论个和尚》郭德纲 于谦", "trackUrl": "/xiangsheng/9723091/46222785", "trackCoverPath": "//imagev2.xmcdn.com/group31/M07/0E/5B/wKgJX1mAQg2SWaYDAAAw0CICWi8444.jpg!op_type=5&upload_type=cover&device_type=ios&name=web_meduim&strip=1&quality=7", "albumId": 9723091, "sourceAlbumId": 9723091, "albumName": "郭德纲21年相声精选", "albumUrl": "/xiangsheng/9723091/", "anchorId": 1000202, "canPlay": true, "isBaiduMusic": false, "isPaid": false, "duration": 2036, "src": "http://audio.xmcdn.com/group30/M02/8E/2E/wKgJXlmEN9bjz0hkAPtM7nK0TUg460.m4a", "hasBuy": true, "albumIsSample": false, "sampleDuration": 0, "updateTime": "1年前", "createTime": "1年前", "isLike": false, "isCopyright": true}, {"index": 135, "trackId": 46222852, "trackName": "《岳满中秋》01", "trackUrl": "/xiangsheng/9723091/46222852", "trackCoverPath": "//imagev2.xmcdn.com/group31/M07/0E/5B/wKgJX1mAQg2SWaYDAAAw0CICWi8444.jpg!op_type=5&upload_type=cover&device_type=ios&name=web_meduim&strip=1&quality=7", "albumId": 9723091, "sourceAlbumId": 9723091, "albumName": "郭德纲21年相声精选", "albumUrl": "/xiangsheng/9723091/", "anchorId": 1000202, "canPlay": true, "isBaiduMusic": false, "isPaid": false, "duration": 3596, "src": "http://audio.xmcdn.com/group30/M02/8E/36/wKgJXlmEOAXxEapsAbvCqJY6vSg450.m4a", "hasBuy": true, "albumIsSample": false, "sampleDuration": 0, "updateTime": "1年前", "createTime": "1年前", "isLike": false, "isCopyright": true}, {"index": 136, "trackId": 46222857, "trackName": "《岳满中秋》02", "trackUrl": "/xiangsheng/9723091/46222857", "trackCoverPath": "//imagev2.xmcdn.com/group31/M07/0E/5B/wKgJX1mAQg2SWaYDAAAw0CICWi8444.jpg!op_type=5&upload_type=cover&device_type=ios&name=web_meduim&strip=1&quality=7", "albumId": 9723091, "sourceAlbumId": 9723091, "albumName": "郭德纲21年相声精选", "albumUrl": "/xiangsheng/9723091/", "anchorId": 1000202, "canPlay": true, "isBaiduMusic": false, "isPaid": false, "duration": 4804, "src": "http://audio.xmcdn.com/group30/M02/8E/3B/wKgJXlmEOBLizumTAlDMSEJOO8I215.m4a", "hasBuy": true, "albumIsSample": false, "sampleDuration": 0, "updateTime": "1年前", "createTime": "1年前", "isLike": false, "isCopyright": true}, {"index": 137, "trackId": 46222726, "trackName": "《曲协主席》郭德纲 于谦", "trackUrl": "/xiangsheng/9723091/46222726", "trackCoverPath": "//imagev2.xmcdn.com/group31/M07/0E/5B/wKgJX1mAQg2SWaYDAAAw0CICWi8444.jpg!op_type=5&upload_type=cover&device_type=ios&name=web_meduim&strip=1&quality=7", "albumId": 9723091, "sourceAlbumId": 9723091, "albumName": "郭德纲21年相声精选", "albumUrl": "/xiangsheng/9723091/", "anchorId": 1000202, "canPlay": true, "isBaiduMusic": false, "isPaid": false, "duration": 523, "src": "http://audio.xmcdn.com/group31/M02/49/55/wKgJSVmEN7vCLqh9AECj6nBWPzE752.m4a", "hasBuy": true, "albumIsSample": false, "sampleDuration": 0, "updateTime": "1年前", "createTime": "1年前", "isLike": false, "isCopyright": true}, {"index": 138, "trackId": 46222860, "trackName": "《人在江湖》郭德纲 于谦", "trackUrl": "/xiangsheng/9723091/46222860", "trackCoverPath": "//imagev2.xmcdn.com/group31/M07/0E/5B/wKgJX1mAQg2SWaYDAAAw0CICWi8444.jpg!op_type=5&upload_type=cover&device_type=ios&name=web_meduim&strip=1&quality=7", "albumId": 9723091, "sourceAlbumId": 9723091, "albumName": "郭德纲21年相声精选", "albumUrl": "/xiangsheng/9723091/", "anchorId": 1000202, "canPlay": true, "isBaiduMusic": false, "isPaid": false, "duration": 1971, "src": "http://audio.xmcdn.com/group30/M02/8E/39/wKgJXlmEN_6jNEimAPM6QCkL_28486.m4a", "hasBuy": true, "albumIsSample": false, "sampleDuration": 0, "updateTime": "7天前", "createTime": "1年前", "isLike": false, "isCopyright": true}, {"index": 139, "trackId": 46329594, "trackName": "《歪批三国》郭德纲 李菁", "trackUrl": "/xiangsheng/9723091/46329594", "trackCoverPath": "//imagev2.xmcdn.com/group31/M07/0E/5B/wKgJX1mAQg2SWaYDAAAw0CICWi8444.jpg!op_type=5&upload_type=cover&device_type=ios&name=web_meduim&strip=1&quality=7", "albumId": 9723091, "sourceAlbumId": 9723091, "albumName": "郭德纲21年相声精选", "albumUrl": "/xiangsheng/9723091/", "anchorId": 1000202, "canPlay": true, "isBaiduMusic": false, "isPaid": false, "duration": 1123, "src": "http://audio.xmcdn.com/group30/M09/B2/D2/wKgJXlmFhwjxvfbDAIqkvpxZP78807.m4a", "hasBuy": true, "albumIsSample": false, "sampleDuration": 0, "updateTime": "1年前", "createTime": "1年前", "isLike": false, "isCopyright": true}, {"index": 140, "trackId": 46329599, "trackName": "你的父亲是和尚 岳云鹏 于谦", "trackUrl": "/xiangsheng/9723091/46329599", "trackCoverPath": "//imagev2.xmcdn.com/group31/M07/0E/5B/wKgJX1mAQg2SWaYDAAAw0CICWi8444.jpg!op_type=5&upload_type=cover&device_type=ios&name=web_meduim&strip=1&quality=7", "albumId": 9723091, "sourceAlbumId": 9723091, "albumName": "郭德纲21年相声精选", "albumUrl": "/xiangsheng/9723091/", "anchorId": 1000202, "canPlay": true, "isBaiduMusic": false, "isPaid": false, "duration": 1449, "src": "http://audio.xmcdn.com/group30/M09/B2/D4/wKgJXlmFhw6zRsZpALLfs20owYA240.m4a", "hasBuy": true, "albumIsSample": false, "sampleDuration": 0, "updateTime": "1年前", "createTime": "1年前", "isLike": false, "isCopyright": true}, {"index": 141, "trackId": 46329604, "trackName": "《美丽人生》郭德纲 于谦", "trackUrl": "/xiangsheng/9723091/46329604", "trackCoverPath": "//imagev2.xmcdn.com/group31/M07/0E/5B/wKgJX1mAQg2SWaYDAAAw0CICWi8444.jpg!op_type=5&upload_type=cover&device_type=ios&name=web_meduim&strip=1&quality=7", "albumId": 9723091, "sourceAlbumId": 9723091, "albumName": "郭德纲21年相声精选", "albumUrl": "/xiangsheng/9723091/", "anchorId": 1000202, "canPlay": true, "isBaiduMusic": false, "isPaid": false, "duration": 734, "src": "http://audio.xmcdn.com/group30/M09/B2/D3/wKgJXlmFhwry_8FSAFqktX_zJbc931.m4a", "hasBuy": true, "albumIsSample": false, "sampleDuration": 0, "updateTime": "1年前", "createTime": "1年前", "isLike": false, "isCopyright": true}, {"index": 142, "trackId": 46329606, "trackName": "《列宁在1918》郭德纲 于谦", "trackUrl": "/xiangsheng/9723091/46329606", "trackCoverPath": "//imagev2.xmcdn.com/group31/M07/0E/5B/wKgJX1mAQg2SWaYDAAAw0CICWi8444.jpg!op_type=5&upload_type=cover&device_type=ios&name=web_meduim&strip=1&quality=7", "albumId": 9723091, "sourceAlbumId": 9723091, "albumName": "郭德纲21年相声精选", "albumUrl": "/xiangsheng/9723091/", "anchorId": 1000202, "canPlay": true, "isBaiduMusic": false, "isPaid": false, "duration": 1711, "src": "http://audio.xmcdn.com/group30/M09/B2/D5/wKgJXlmFhxPxlO2-ANM1Mmea-sk802.m4a", "hasBuy": true, "albumIsSample": false, "sampleDuration": 0, "updateTime": "1年前", "createTime": "1年前", "isLike": false, "isCopyright": true}, {"index": 143, "trackId": 46329607, "trackName": "《跟嫂子学艺》 郭德纲 于谦", "trackUrl": "/xiangsheng/9723091/46329607", "trackCoverPath": "//imagev2.xmcdn.com/group31/M07/0E/5B/wKgJX1mAQg2SWaYDAAAw0CICWi8444.jpg!op_type=5&upload_type=cover&device_type=ios&name=web_meduim&strip=1&quality=7", "albumId": 9723091, "sourceAlbumId": 9723091, "albumName": "郭德纲21年相声精选", "albumUrl": "/xiangsheng/9723091/", "anchorId": 1000202, "canPlay": true, "isBaiduMusic": false, "isPaid": false, "duration": 1819, "src": "http://audio.xmcdn.com/group30/M09/B2/D6/wKgJXlmFhxbj9pKhAOCFHX9TbfY839.m4a", "hasBuy": true, "albumIsSample": false, "sampleDuration": 0, "updateTime": "1年前", "createTime": "1年前", "isLike": false, "isCopyright": true}, {"index": 144, "trackId": 46329695, "trackName": "《我在妓校的那几年》郭德纲 于谦", "trackUrl": "/xiangsheng/9723091/46329695", "trackCoverPath": "//imagev2.xmcdn.com/group31/M07/0E/5B/wKgJX1mAQg2SWaYDAAAw0CICWi8444.jpg!op_type=5&upload_type=cover&device_type=ios&name=web_meduim&strip=1&quality=7", "albumId": 9723091, "sourceAlbumId": 9723091, "albumName": "郭德纲21年相声精选", "albumUrl": "/xiangsheng/9723091/", "anchorId": 1000202, "canPlay": true, "isBaiduMusic": false, "isPaid": false, "duration": 2342, "src": "http://audio.xmcdn.com/group31/M04/5B/9C/wKgJSVmFh0PwbcDsASESrUfWyPo447.m4a", "hasBuy": true, "albumIsSample": false, "sampleDuration": 0, "updateTime": "1年前", "createTime": "1年前", "isLike": false, "isCopyright": true}, {"index": 145, "trackId": 46329657, "trackName": "《泰国归来》郭德纲 于谦", "trackUrl": "/xiangsheng/9723091/46329657", "trackCoverPath": "//imagev2.xmcdn.com/group31/M07/0E/5B/wKgJX1mAQg2SWaYDAAAw0CICWi8444.jpg!op_type=5&upload_type=cover&device_type=ios&name=web_meduim&strip=1&quality=7", "albumId": 9723091, "sourceAlbumId": 9723091, "albumName": "郭德纲21年相声精选", "albumUrl": "/xiangsheng/9723091/", "anchorId": 1000202, "canPlay": true, "isBaiduMusic": false, "isPaid": false, "duration": 1691, "src": "http://audio.xmcdn.com/group31/M04/5B/B5/wKgJX1mFhz2j6kcSANC1xE9dy-U105.m4a", "hasBuy": true, "albumIsSample": false, "sampleDuration": 0, "updateTime": "1年前", "createTime": "1年前", "isLike": false, "isCopyright": true}, {"index": 146, "trackId": 46329608, "trackName": "《谁动了我的减肥茶》郭德纲 于谦", "trackUrl": "/xiangsheng/9723091/46329608", "trackCoverPath": "//imagev2.xmcdn.com/group31/M07/0E/5B/wKgJX1mAQg2SWaYDAAAw0CICWi8444.jpg!op_type=5&upload_type=cover&device_type=ios&name=web_meduim&strip=1&quality=7", "albumId": 9723091, "sourceAlbumId": 9723091, "albumName": "郭德纲21年相声精选", "albumUrl": "/xiangsheng/9723091/", "anchorId": 1000202, "canPlay": true, "isBaiduMusic": false, "isPaid": false, "duration": 885, "src": "http://audio.xmcdn.com/group30/M09/B2/D6/wKgJXlmFhxXwqORkAG1Cf_WzBiY894.m4a", "hasBuy": true, "albumIsSample": false, "sampleDuration": 0, "updateTime": "1年前", "createTime": "1年前", "isLike": false, "isCopyright": true}, {"index": 147, "trackId": 46329659, "trackName": "《杨乃武写状》郭德纲 于谦", "trackUrl": "/xiangsheng/9723091/46329659", "trackCoverPath": "//imagev2.xmcdn.com/group31/M07/0E/5B/wKgJX1mAQg2SWaYDAAAw0CICWi8444.jpg!op_type=5&upload_type=cover&device_type=ios&name=web_meduim&strip=1&quality=7", "albumId": 9723091, "sourceAlbumId": 9723091, "albumName": "郭德纲21年相声精选", "albumUrl": "/xiangsheng/9723091/", "anchorId": 1000202, "canPlay": true, "isBaiduMusic": false, "isPaid": false, "duration": 1536, "src": "http://audio.xmcdn.com/group31/M04/5B/B5/wKgJX1mFh0HD3llXAL2bGsGpbHI738.m4a", "hasBuy": true, "albumIsSample": false, "sampleDuration": 0, "updateTime": "1年前", "createTime": "1年前", "isLike": false, "isCopyright": true}, {"index": 148, "trackId": 46329660, "trackName": "《论50年之现状》郭德纲 于谦", "trackUrl": "/xiangsheng/9723091/46329660", "trackCoverPath": "//imagev2.xmcdn.com/group31/M07/0E/5B/wKgJX1mAQg2SWaYDAAAw0CICWi8444.jpg!op_type=5&upload_type=cover&device_type=ios&name=web_meduim&strip=1&quality=7", "albumId": 9723091, "sourceAlbumId": 9723091, "albumName": "郭德纲21年相声精选", "albumUrl": "/xiangsheng/9723091/", "anchorId": 1000202, "canPlay": true, "isBaiduMusic": false, "isPaid": false, "duration": 1231, "src": "http://audio.xmcdn.com/group31/M04/5B/9B/wKgJSVmFhz2wVzCkAJftEJb5Ykg120.m4a", "hasBuy": true, "albumIsSample": false, "sampleDuration": 0, "updateTime": "1年前", "createTime": "1年前", "isLike": false, "isCopyright": true}, {"index": 149, "trackId": 46329700, "trackName": "《大学生涯》郭德纲 于谦", "trackUrl": "/xiangsheng/9723091/46329700", "trackCoverPath": "//imagev2.xmcdn.com/group31/M07/0E/5B/wKgJX1mAQg2SWaYDAAAw0CICWi8444.jpg!op_type=5&upload_type=cover&device_type=ios&name=web_meduim&strip=1&quality=7", "albumId": 9723091, "sourceAlbumId": 9723091, "albumName": "郭德纲21年相声精选", "albumUrl": "/xiangsheng/9723091/", "anchorId": 1000202, "canPlay": true, "isBaiduMusic": false, "isPaid": false, "duration": 1934, "src": "http://audio.xmcdn.com/group31/M04/5B/B8/wKgJX1mFh1qQ1xl3AO7GbfN9zVo946.m4a", "hasBuy": true, "albumIsSample": false, "sampleDuration": 0, "updateTime": "1年前", "createTime": "1年前", "isLike": false, "isCopyright": true}, {"index": 150, "trackId": 46329705, "trackName": "《讲笑话》郭德纲 于谦", "trackUrl": "/xiangsheng/9723091/46329705", "trackCoverPath": "//imagev2.xmcdn.com/group31/M07/0E/5B/wKgJX1mAQg2SWaYDAAAw0CICWi8444.jpg!op_type=5&upload_type=cover&device_type=ios&name=web_meduim&strip=1&quality=7", "albumId": 9723091, "sourceAlbumId": 9723091, "albumName": "郭德纲21年相声精选", "albumUrl": "/xiangsheng/9723091/", "anchorId": 1000202, "canPlay": true, "isBaiduMusic": false, "isPaid": false, "duration": 1646, "src": "http://audio.xmcdn.com/group31/M04/5B/B8/wKgJX1mFh1iB0Ib3AMskB3Y1gG8348.m4a", "hasBuy": true, "albumIsSample": false, "sampleDuration": 0, "updateTime": "1年前", "createTime": "1年前", "isLike": false, "isCopyright": true}], "hasMore": true}}